cruz/__init__.py
cruz/election2022.py
cruz-1.2.0.dist-info/LICENSE
cruz-1.2.0.dist-info/WHEEL
cruz-1.2.0.dist-info/METADATA
cruz-1.2.0.dist-info/RECORD
