Metadata-Version: 2.1
Name: cruz
Version: 1.2.0
Summary: 
Author: Kyle Kelley
Author-email: rgbkrk@gmail.com
Requires-Python: >=3.9,<4.0
Classifier: Programming Language :: Python :: 3
Classifier: Programming Language :: Python :: 3.10
Classifier: Programming Language :: Python :: 3.9
Requires-Dist: pandas (>=1.4.3,<2.0.0)
Requires-Dist: pyarrow (>=9.0.0,<10.0.0)
Requires-Dist: requests (>=2.28.1,<3.0.0)
